papurika/__init__.py
papurika/channel.py
papurika/server.py
papurika/service.py
papurika-0.2.0.dist-info/LICENSE
papurika-0.2.0.dist-info/WHEEL
papurika-0.2.0.dist-info/METADATA
papurika-0.2.0.dist-info/RECORD
