Metadata-Version: 2.1
Name: papurika
Version: 0.2.0
Summary: 
License: BSD-3-Clause
Author: Hanaasagi
Author-email: ambiguous404@gmail.com
Requires-Python: >=3.6,<4.0
Classifier: License :: OSI Approved :: BSD License
Classifier: Programming Language :: Python :: 3
Classifier: Programming Language :: Python :: 3.6
Classifier: Programming Language :: Python :: 3.7
Classifier: Programming Language :: Python :: 3.8
Requires-Dist: grpcio (>=1.26.0,<2.0.0)
Requires-Dist: grpcio-tools (>=1.26.0,<2.0.0)
